{"commitInfo":{"timestamp":1750309905213,"userId":"8778822765517627","userName":"azuser3551_mml.local@techademy.com","operation":"WRITE","operationParameters":{"mode":"Overwrite","statsOnLoad":false,"partitionBy":"[]"},"notebook":{"notebookId":"3072619134359928"},"clusterId":"0611-043435-vg20yowf","isolationLevel":"WriteSerializable","isBlindAppend":false,"operationMetrics":{"numFiles":"1","numOutputRows":"5","numOutputBytes":"3490"},"tags":{"noRowsCopied":"true","restoresDeletedRows":"false"},"engineInfo":"Databricks-Runtime/15.4.x-photon-scala2.12","txnId":"a0e66425-0153-4616-af2e-0472069cbdd5"}}
{"metaData":{"id":"1a9f66d2-e3ad-4fc3-a313-2fccfb54f4fc","format":{"provider":"parquet","options":{}},"schemaString":"{\"type\":\"struct\",\"fields\":[{\"name\":\"ItemID\",\"type\":\"string\",\"nullable\":true,\"metadata\":{}},{\"name\":\"ItemName\",\"type\":\"string\",\"nullable\":true,\"metadata\":{}},{\"name\":\"Category\",\"type\":\"string\",\"nullable\":true,\"metadata\":{}},{\"name\":\"Warehouse\",\"type\":\"string\",\"nullable\":true,\"metadata\":{}},{\"name\":\"StockQty\",\"type\":\"integer\",\"nullable\":true,\"metadata\":{}},{\"name\":\"ReorderLevel\",\"type\":\"integer\",\"nullable\":true,\"metadata\":{}},{\"name\":\"LastRestocked\",\"type\":\"date\",\"nullable\":true,\"metadata\":{\"__detected_date_formats\":\"yyyy-M-d\"}},{\"name\":\"UnitPrice\",\"type\":\"integer\",\"nullable\":true,\"metadata\":{}},{\"name\":\"Supplier\",\"type\":\"string\",\"nullable\":true,\"metadata\":{}},{\"name\":\"NeedsReorder\",\"type\":\"boolean\",\"nullable\":true,\"metadata\":{}},{\"name\":\"CategoryAvg\",\"type\":\"double\",\"nullable\":true,\"metadata\":{}},{\"name\":\"BelowCategoryAvg\",\"type\":\"boolean\",\"nullable\":true,\"metadata\":{}},{\"name\":\"TotalStockValue\",\"type\":\"integer\",\"nullable\":true,\"metadata\":{}}]}","partitionColumns":[],"configuration":{"delta.enableDeletionVectors":"true"},"createdTime":1750309904007}}
{"protocol":{"minReaderVersion":3,"minWriterVersion":7,"readerFeatures":["deletionVectors"],"writerFeatures":["deletionVectors"]}}
{"add":{"path":"part-00000-9b090f49-f11a-44c3-bad0-5c434ff66035.c000.snappy.parquet","partitionValues":{},"size":3490,"modificationTime":1750309904749,"dataChange":true,"stats":"{\"numRecords\":5,\"minValues\":{\"ItemID\":\"I001\",\"ItemName\":\"LED TV\",\"Category\":\"Appliances\",\"Warehouse\":\"WarehouseA\",\"StockQty\":3,\"ReorderLevel\":5,\"LastRestocked\":\"2024-02-20\",\"UnitPrice\":6000,\"Supplier\":\"AVTech\",\"CategoryAvg\":6000.0,\"TotalStockValue\":24000},\"maxValues\":{\"ItemID\":\"I005\",\"ItemName\":\"Refrigerator\",\"Category\":\"Furniture\",\"Warehouse\":\"WarehouseC\",\"StockQty\":50,\"ReorderLevel\":20,\"LastRestocked\":\"2024-04-01\",\"UnitPrice\":70000,\"Supplier\":\"TechWorld\",\"CategoryAvg\":36000.0,\"TotalStockValue\":1500000},\"nullCount\":{\"ItemID\":0,\"ItemName\":0,\"Category\":0,\"Warehouse\":0,\"StockQty\":0,\"ReorderLevel\":0,\"LastRestocked\":0,\"UnitPrice\":0,\"Supplier\":0,\"NeedsReorder\":0,\"CategoryAvg\":0,\"BelowCategoryAvg\":0,\"TotalStockValue\":0},\"tightBounds\":true}","tags":{"INSERTION_TIME":"1750309904749000","MIN_INSERTION_TIME":"1750309904749000","MAX_INSERTION_TIME":"1750309904749000","OPTIMIZE_TARGET_SIZE":"268435456"}}}
